veee/__init__.py
veee/exception/__init__.py
veee/exception/api_error.py
veee/platform/__init__.py
veee/platform/bluesky.py
veee/platform/facebook.py
veee/platform/google.py
veee/platform/instagram.py
veee/platform/integration.py
veee/platform/linkedin.py
veee/platform/linkedin_page.py
veee/platform/pinterest.py
veee/platform/snapchat.py
veee/platform/threads.py
veee/platform/tiktok.py
veee/platform/twitter.py
veee/platform/youtube.py
veee/util/__init__.py
veee/util/file_system.py
veee/util/logger.py
veee-0.0.20.dist-info/licenses/LICENSE.txt
veee-0.0.20.dist-info/METADATA
veee-0.0.20.dist-info/WHEEL
veee-0.0.20.dist-info/top_level.txt
veee-0.0.20.dist-info/RECORD
