Metadata-Version: 2.4
Name: veee
Version: 0.0.20
Summary: API Integrations for Social Media Platforms
Home-page: https://github.com/clivern/veee/
Author: clivern
Author-email: hello@clivern.com
License: Apache Software License
Project-URL: Documentation, https://github.com/clivern/veee/
Project-URL: Source, https://github.com/clivern/veee/
Project-URL: Changelog, https://github.com/clivern/veee/blob/main/CHANGELOG.rst
Project-URL: Tracker, https://github.com/clivern/veee/issues
Project-URL: Download, https://pypi.org/project/veee/#files
Platform: any
Classifier: Development Status :: 5 - Production/Stable
Classifier: Programming Language :: Python
Classifier: License :: OSI Approved :: Apache Software License
License-File: LICENSE.txt
Requires-Dist: requests<=2.32.5
Requires-Dist: tweepy<=4.16.0
Requires-Dist: importlib-metadata; python_version < "3.8"
Dynamic: license-file
